djangocms_timed_publishing/__init__.py
djangocms_timed_publishing/apps.py
djangocms_timed_publishing/cms_config.py
djangocms_timed_publishing/cms_toolbars.py
djangocms_timed_publishing/forms.py
djangocms_timed_publishing/models.py
djangocms_timed_publishing/locale/de/LC_MESSAGES/django.mo
djangocms_timed_publishing/locale/de/LC_MESSAGES/django.po
djangocms_timed_publishing/locale/en/LC_MESSAGES/django.mo
djangocms_timed_publishing/locale/en/LC_MESSAGES/django.po
djangocms_timed_publishing/migrations/0001_initial.py
djangocms_timed_publishing/migrations/__init__.py
djangocms_timed_publishing/templates/djangocms_versioning/admin/timed_publishing.html
djangocms_timed_publishing-0.2.0.dist-info/licenses/LICENSE
djangocms_timed_publishing-0.2.0.dist-info/METADATA
djangocms_timed_publishing-0.2.0.dist-info/WHEEL
djangocms_timed_publishing-0.2.0.dist-info/top_level.txt
djangocms_timed_publishing-0.2.0.dist-info/RECORD
