Metadata-Version: 2.4
Name: djangocms-timed-publishing
Version: 0.2.0
Summary: djangocms-versioning extension to time your publications
Author: fsbraun
License: BSD 3-Clause License
Project-URL: Bug Reports, https://github.com/fsbraun/djangocms-timed-publishing/issues
Project-URL: Homepage, https://github.com/fsbraun/djangocms-timed-publishing
Project-URL: Source, https://github.com/fsbraun/djangocms-timed-publishing
Keywords: cms,django,djangocms,publications,timed,versioning
Classifier: Development Status :: 3 - Alpha
Classifier: Framework :: Django
Classifier: Framework :: Django :: 4.2
Classifier: Framework :: Django :: 5.0
Classifier: Framework :: Django :: 5.1
Classifier: Framework :: Django :: 5.2
Classifier: Framework :: Django CMS
Classifier: Framework :: Django CMS :: 4.1
Classifier: Framework :: Django CMS :: 5.0
Classifier: Intended Audience :: Developers
Classifier: License :: OSI Approved :: MIT License
Classifier: Operating System :: OS Independent
Classifier: Programming Language :: Python
Classifier: Programming Language :: Python :: 3 :: Only
Classifier: Programming Language :: Python :: 3.9
Classifier: Programming Language :: Python :: 3.10
Classifier: Programming Language :: Python :: 3.11
Classifier: Programming Language :: Python :: 3.12
Classifier: Programming Language :: Python :: 3.13
Classifier: Topic :: Internet :: WWW/HTTP
Classifier: Topic :: Internet :: WWW/HTTP :: Dynamic Content
Classifier: Topic :: Software Development
Classifier: Topic :: Software Development :: Libraries
Requires-Python: >=3.9
License-File: LICENSE
Requires-Dist: django-cms>=4.1
Requires-Dist: djangocms-versioning>=2
Provides-Extra: dev
Requires-Dist: black; extra == "dev"
Requires-Dist: coverage; extra == "dev"
Requires-Dist: flake8; extra == "dev"
Requires-Dist: isort; extra == "dev"
Requires-Dist: pytest; extra == "dev"
Requires-Dist: pytest-django; extra == "dev"
Requires-Dist: tox; extra == "dev"
Provides-Extra: test
Requires-Dist: coverage; extra == "test"
Requires-Dist: pytest; extra == "test"
Requires-Dist: pytest-django; extra == "test"
Dynamic: license-file
